MANIFEST.in
README.md
setup.cfg
setup.py
versioneer.py
./bhmm/_external/clustering/src/clustering.c
./bhmm/_external/clustering/src/kmeans.c
./bhmm/hidden/impl_c/_hidden.c
./bhmm/hidden/impl_c/hidden.c
./bhmm/output_models/impl_c/_discrete.c
./bhmm/output_models/impl_c/_gaussian.c
./bhmm/output_models/impl_c/discrete.c
./bhmm/output_models/impl_c/gaussian.c
bhmm/__init__.py
bhmm/api.py
bhmm/version.py
bhmm.egg-info/PKG-INFO
bhmm.egg-info/SOURCES.txt
bhmm.egg-info/dependency_links.txt
bhmm.egg-info/not-zip-safe
bhmm.egg-info/requires.txt
bhmm.egg-info/top_level.txt
bhmm/_external/__init__.py
bhmm/_external/clustering/__init__.py
bhmm/_external/clustering/include/clustering.h
bhmm/_external/clustering/src/clustering.c
bhmm/_external/clustering/src/kmeans.c
bhmm/_external/sklearn/__init__.py
bhmm/_external/sklearn/base.py
bhmm/_external/sklearn/utils.py
bhmm/_external/sklearn/mixture/__init__.py
bhmm/_external/sklearn/mixture/gmm.py
bhmm/estimators/__init__.py
bhmm/estimators/_tmatrix_disconnected.py
bhmm/estimators/bayesian_sampling.py
bhmm/estimators/maximum_likelihood.py
bhmm/hidden/__init__.py
bhmm/hidden/api.py
bhmm/hidden/impl_c/__init__.py
bhmm/hidden/impl_c/_hidden.c
bhmm/hidden/impl_c/_hidden.h
bhmm/hidden/impl_c/hidden.c
bhmm/hidden/impl_c/hidden.pyx
bhmm/hidden/impl_python/__init__.py
bhmm/hidden/impl_python/hidden.py
bhmm/hmm/__init__.py
bhmm/hmm/discrete_hmm.py
bhmm/hmm/gaussian_hmm.py
bhmm/hmm/generic_hmm.py
bhmm/hmm/generic_sampled_hmm.py
bhmm/init/__init__.py
bhmm/init/discrete.py
bhmm/init/gaussian.py
bhmm/output_models/__init__.py
bhmm/output_models/discrete.py
bhmm/output_models/gaussian.py
bhmm/output_models/outputmodel.py
bhmm/output_models/impl_c/__init__.py
bhmm/output_models/impl_c/_discrete.c
bhmm/output_models/impl_c/_discrete.h
bhmm/output_models/impl_c/_gaussian.c
bhmm/output_models/impl_c/_gaussian.h
bhmm/output_models/impl_c/discrete.c
bhmm/output_models/impl_c/discrete.pyx
bhmm/output_models/impl_c/gaussian.c
bhmm/output_models/impl_c/gaussian.pyx
bhmm/tests/__init__.py
bhmm/tests/benchmark_hidden.py
bhmm/tests/test_bhmm.py
bhmm/tests/test_bhmm_patho.py
bhmm/tests/test_hidden.py
