Metadata-Version: 1.1
Name: bhmm
Version: 0.6.2
Summary:  BHMM: A toolkit for Bayesian hidden Markov model analysis of single-molecule trajectories.
Home-page: https://github.com/bhmm/bhmm
Author: John Chodera and Frank Noe
Author-email: john.chodera@choderalab.org
License: LGPL
Platform: Linux
Platform: Mac OS-X
Platform: Unix
Platform: Windows
Classifier: Development Status :: 3 - Alpha
Classifier: Intended Audience :: Science/Research
Classifier: Intended Audience :: Developers
Classifier: License :: OSI Approved :: GNU Lesser General Public License v3 (LGPLv3)
Classifier: Programming Language :: Python
Classifier: Topic :: Scientific/Engineering :: Bio-Informatics
Classifier: Topic :: Scientific/Engineering :: Chemistry
Classifier: Operating System :: Microsoft :: Windows
Classifier: Operating System :: POSIX
Classifier: Operating System :: Unix
Classifier: Operating System :: MacOS
